qdrant_loader_mcp_server/__init__.py
qdrant_loader_mcp_server/__main__.py
qdrant_loader_mcp_server/cli.py
qdrant_loader_mcp_server/config.py
qdrant_loader_mcp_server/config_loader.py
qdrant_loader_mcp_server/main.py
qdrant_loader_mcp_server/mcp/__init__.py
qdrant_loader_mcp_server/mcp/formatters.py
qdrant_loader_mcp_server/mcp/handler.py
qdrant_loader_mcp_server/mcp/intelligence_handler.py
qdrant_loader_mcp_server/mcp/models.py
qdrant_loader_mcp_server/mcp/protocol.py
qdrant_loader_mcp_server/mcp/schemas.py
qdrant_loader_mcp_server/mcp/search_handler.py
qdrant_loader_mcp_server/mcp/formatters/__init__.py
qdrant_loader_mcp_server/mcp/formatters/basic.py
qdrant_loader_mcp_server/mcp/formatters/intelligence.py
qdrant_loader_mcp_server/mcp/formatters/lightweight.py
qdrant_loader_mcp_server/mcp/formatters/structured.py
qdrant_loader_mcp_server/mcp/formatters/utils.py
qdrant_loader_mcp_server/mcp/handlers/intelligence/__init__.py
qdrant_loader_mcp_server/mcp/handlers/intelligence/relationships.py
qdrant_loader_mcp_server/mcp/handlers/intelligence/utils.py
qdrant_loader_mcp_server/mcp/handlers/search/__init__.py
qdrant_loader_mcp_server/mcp/handlers/search/filters.py
qdrant_loader_mcp_server/mcp/handlers/search/formatting.py
qdrant_loader_mcp_server/mcp/handlers/search/organize.py
qdrant_loader_mcp_server/mcp/schemas/__init__.py
qdrant_loader_mcp_server/mcp/schemas/analyze_relationships.py
qdrant_loader_mcp_server/mcp/schemas/attachment.py
qdrant_loader_mcp_server/mcp/schemas/cluster_documents.py
qdrant_loader_mcp_server/mcp/schemas/detect_conflicts.py
qdrant_loader_mcp_server/mcp/schemas/expand_cluster.py
qdrant_loader_mcp_server/mcp/schemas/expand_document.py
qdrant_loader_mcp_server/mcp/schemas/find_complementary.py
qdrant_loader_mcp_server/mcp/schemas/find_similar.py
qdrant_loader_mcp_server/mcp/schemas/hierarchy.py
qdrant_loader_mcp_server/mcp/schemas/search.py
qdrant_loader_mcp_server/search/__init__.py
qdrant_loader_mcp_server/search/engine.py
qdrant_loader_mcp_server-0.7.6.dist-info/METADATA
qdrant_loader_mcp_server-0.7.6.dist-info/WHEEL
qdrant_loader_mcp_server-0.7.6.dist-info/entry_points.txt
qdrant_loader_mcp_server-0.7.6.dist-info/top_level.txt
qdrant_loader_mcp_server-0.7.6.dist-info/RECORD
