Metadata-Version: 2.4
Name: qdrant-loader-mcp-server
Version: 0.7.6
Summary: A Model Context Protocol (MCP) server that provides RAG capabilities to Cursor using Qdrant.
Author-email: Martin Papy <martin.papy@cbtw.tech>
License-Expression: GPL-3.0
Project-URL: Homepage, https://qdrant-loader.net
Project-URL: Documentation, https://qdrant-loader.net/docs/packages/mcp-server/README.html
Project-URL: Repository, https://github.com/martin-papy/qdrant-loader
Project-URL: Issues, https://github.com/martin-papy/qdrant-loader/issues
Keywords: qdrant,vector-database,mcp,cursor,rag,embeddings,multi-project,semantic-search
Classifier: Development Status :: 5 - Production/Stable
Classifier: Intended Audience :: Developers
Classifier: Intended Audience :: Information Technology
Classifier: Operating System :: OS Independent
Classifier: Programming Language :: Python :: 3
Classifier: Programming Language :: Python :: 3.12
Classifier: Topic :: Database
Classifier: Topic :: Scientific/Engineering :: Artificial Intelligence
Classifier: Topic :: Software Development :: Libraries :: Python Modules
Classifier: Topic :: Text Processing :: Indexing
Classifier: Topic :: Internet :: WWW/HTTP :: HTTP Servers
Classifier: Environment :: Console
Classifier: Framework :: FastAPI
Classifier: Typing :: Typed
Requires-Python: >=3.12
Requires-Dist: fastapi>=0.104.0
Requires-Dist: uvicorn>=0.24.0
Requires-Dist: qdrant-client>=1.6.0
Requires-Dist: openai>=1.3.0
Requires-Dist: pydantic>=2.4.2
Requires-Dist: python-dotenv>=1.0.0
Requires-Dist: jsonrpcclient>=4.0.3
Requires-Dist: jsonrpcserver>=5.0.7
Requires-Dist: structlog>=23.0.0
Requires-Dist: PyYAML>=6.0.0
Requires-Dist: rank-bm25>=0.2.2
Requires-Dist: numpy>=1.26.0
Requires-Dist: click>=8.0.0
Requires-Dist: tomli>=2.0.0
Requires-Dist: networkx>=3.0.0
Requires-Dist: spacy>=3.7.0
Requires-Dist: qdrant-loader-core==0.7.6
